{
  "FileVersion": "1.0",
  "InactiveMembersInReports": true,
  "InactiveMembersInLists": true,
  "ClubRoster": [],
  "RaceClasses": [],
  "Locations": [],
  "Contests": [
    {
      "ContestDate": "2020-08-03T00:00:00-06:00",
      "Location": "",
      "RaceClass": "",
      "Status": "OK",
      "Rounds": 8,
      "Pilots": 1,
      "Notes": "",
      "Scoreboard": [
        {
          "Place": "1",
          "Pilot": "Kevin",
          "HeatTimes": [
            "NT",
            "NT",
            "NT",
            "NT",
            "NT",
            "NT",
            "NT",
            "NT"
          ]
        }
      ]
    }
  ]
}